dspy_file/__init__.py
dspy_file/analyze_file_cli.py
dspy_file/file_analyzer.py
dspy_file/file_helpers.py
dspy_file/refactor_analyzer.py
dspy_file/signatures.py
dspy_file/prompts/__init__.py
dspy_file/prompts/refactor_prompt_template.md
dspyteach-0.1.10b1.dist-info/METADATA
dspyteach-0.1.10b1.dist-info/WHEEL
dspyteach-0.1.10b1.dist-info/entry_points.txt
dspyteach-0.1.10b1.dist-info/top_level.txt
dspyteach-0.1.10b1.dist-info/RECORD
