Metadata-Version: 2.4
Name: dspyteach
Version: 0.1.10b1
Summary: CLI utility that summarizes single files into teaching briefs using DSPy, with optional MLflow tracking
Author: DSPy File Maintainers
Keywords: dspy,teaching,summaries,cli,mlflow,tracking
Classifier: Programming Language :: Python :: 3
Classifier: Programming Language :: Python :: 3.10
Classifier: Programming Language :: Python :: 3.11
Classifier: Operating System :: OS Independent
Classifier: Topic :: Software Development :: Code Generators
Requires-Python: <3.12,>=3.10
Requires-Dist: dspy>=2.6
Requires-Dist: pytest>=8.4.2
Requires-Dist: python-dotenv>=1.0
Provides-Extra: mlflow
Requires-Dist: mlflow<4,>=3.3; extra == "mlflow"
